[
    {
        "number": "2021- 00001154901",
        "date": "06 juillet 2021",
        "denomination": "CONFEDERATION DES ORGANISATIONS PATRONALES CEDEAO POUR L’INDUSTRIE TOURISTIQUE ONE AUX PERSONNES CIAPRES DESIGNEES RECEPISSE DE DECLARATION D’EXISTENCE POUR L’ASSOCIATION REGIE PAR LA LOI N° 0642015CNT DU 20 OCTOBRE 2015 PORTANT LIBERTE D’ASSOCIATION DEN OMINATION ASSOCIATION HUMANITAIRE DENTIFILI D IEGE OUAGADOUGOU ADRESSE TEL79 12 63 55",
        "objective": "Creer un cadre federateur de promotion et de developpement du tourisme dans l’espace cedeao",
        "abbreviation": "",
        "siege": "OUAGADOUGOU ADRESSE TEL 70 21 15 26 DOMAINE D’INTERVENTION PROTECTION DES GROUPES SPECIFIQUES DOMAINE D’INTERVENTION PROMOTION DU SECTEUR PRIVE",
        "id": "52e96e3606023e56bd1ab398041ae53d",
        "journal_link": "https://www.loc.gov/resource/llflg.87648643_20210902_01"
    }
]